schemarin/LICENSE.md
schemarin/__init__.py
schemarin/helpers.py
schemarin/importers.py
schemarin/prompts.py
schemarin/protected.toml
schemarin/schemarin.py
schemarin-1.0.1.dist-info/entry_points.txt
schemarin-1.0.1.dist-info/LICENSE.md
schemarin-1.0.1.dist-info/WHEEL
schemarin-1.0.1.dist-info/METADATA
schemarin-1.0.1.dist-info/RECORD
